encode_utils/__init__.py
encode_utils/attachment.py
encode_utils/aws_storage.py
encode_utils/connection.py
encode_utils/parent_argparser.py
encode_utils/profiles.py
encode_utils/replicate.py
encode_utils/transfer_to_gcp.py
encode_utils/utils.py
encode_utils/MetaDataRegistration/__init__.py
encode_utils/MetaDataRegistration/eu_register.py
encode_utils/scripts/__init__.py
encode_utils/scripts/eu_add_controlled_by.py
encode_utils/scripts/eu_check_not_posted.py
encode_utils/scripts/eu_create_gcp_url_list.py
encode_utils/scripts/eu_generate_upload_creds.py
encode_utils/scripts/eu_get_accessions.py
encode_utils/scripts/eu_get_aliases.py
encode_utils/scripts/eu_get_replicate_fastq_encffs.py
encode_utils/scripts/eu_get_replicate_numbers.py
encode_utils/scripts/eu_patch_property.py
encode_utils/scripts/eu_report_fastq_content_errors.py
encode_utils/scripts/eu_s3_to_gcp.py
encode_utils/scripts/eu_search_results_json.py
encode_utils/tests/__init__.py
encode_utils/tests/test_connection.py
encode_utils/tests/test_eu_register.py
encode_utils/tests/test_utils.py
encode_utils/tests/data/estarr_counts.as
encode_utils/tests/data/replicates_for_ENCSR502NRF.json
encode_utils/tests/data/test_fq_40recs.fastq.gz
encode_utils-2.10.0.data/scripts/eu_add_controlled_by.py
encode_utils-2.10.0.data/scripts/eu_check_not_posted.py
encode_utils-2.10.0.data/scripts/eu_create_gcp_url_list.py
encode_utils-2.10.0.data/scripts/eu_generate_upload_creds.py
encode_utils-2.10.0.data/scripts/eu_get_accessions.py
encode_utils-2.10.0.data/scripts/eu_get_aliases.py
encode_utils-2.10.0.data/scripts/eu_get_replicate_fastq_encffs.py
encode_utils-2.10.0.data/scripts/eu_get_replicate_numbers.py
encode_utils-2.10.0.data/scripts/eu_patch_property.py
encode_utils-2.10.0.data/scripts/eu_register.py
encode_utils-2.10.0.data/scripts/eu_report_fastq_content_errors.py
encode_utils-2.10.0.data/scripts/eu_s3_to_gcp.py
encode_utils-2.10.0.data/scripts/eu_search_results_json.py
encode_utils-2.10.0.dist-info/LICENSE.txt
encode_utils-2.10.0.dist-info/METADATA
encode_utils-2.10.0.dist-info/WHEEL
encode_utils-2.10.0.dist-info/top_level.txt
encode_utils-2.10.0.dist-info/RECORD
