Metadata-Version: 2.1
Name: encode-utils
Version: 2.10.0
Summary: Client and tools for ENCODE data submitters.
Home-page: https://github.com/StanfordBioinformatics/encode_utils
Author: Nathaniel Watson
Author-email: nathankw@stanford.edu
License: UNKNOWN
Project-URL: Read the Docs, https://encode-utils.readthedocs.io/en/latest
Platform: UNKNOWN
Classifier: Programming Language :: Python :: 3
Classifier: License :: OSI Approved :: MIT License
Classifier: Operating System :: OS Independent
Requires-Dist: awscli
Requires-Dist: boto3
Requires-Dist: exifread
Requires-Dist: google-api-python-client
Requires-Dist: inflection
Requires-Dist: jsonschema
Requires-Dist: pillow
Requires-Dist: requests
Requires-Dist: urllib3
Provides-Extra: dev
Requires-Dist: pytest ; extra == 'dev'
